{
	"credit": "Made with Blockbench",
	"texture_size": [32, 32],
	"textures": {
		"3": "returntosoil:blocks/lilypad_lantern/lilypad_lantern_7n",
		"particle": "returntosoil:blocks/lilypad_lantern/lilypad_lantern_1n"
	},
	"elements": [
		{
			"from": [6.5, 0, 5.5],
			"to": [10.5, 6, 9.5],
			"faces": {
				"north": {"uv": [7, 6, 9, 9], "texture": "#3"},
				"east": {"uv": [7, 6, 9, 9], "texture": "#3"},
				"south": {"uv": [7, 6, 9, 9], "texture": "#3"},
				"west": {"uv": [7, 6, 9, 9], "texture": "#3"},
				"up": {"uv": [12, 2, 10, 0], "texture": "#3"},
				"down": {"uv": [12, 2, 10, 4], "texture": "#3"}
			}
		},
		{
			"from": [6, 0, 5],
			"to": [7, 6, 6],
			"faces": {
				"north": {"uv": [11.5, 7, 12, 10], "texture": "#3"},
				"east": {"uv": [11.5, 10, 12, 13], "texture": "#3"},
				"south": {"uv": [12, 0, 12.5, 3], "texture": "#3"},
				"west": {"uv": [12, 3, 12.5, 6], "texture": "#3"},
				"up": {"uv": [10.5, 5.5, 10, 5], "texture": "#3"},
				"down": {"uv": [10.5, 5.5, 10, 6], "texture": "#3"}
			}
		},
		{
			"from": [10, 0, 5],
			"to": [11, 6, 6],
			"faces": {
				"north": {"uv": [12, 6, 12.5, 9], "texture": "#3"},
				"east": {"uv": [7, 12, 7.5, 15], "texture": "#3"},
				"south": {"uv": [7.5, 12, 8, 15], "texture": "#3"},
				"west": {"uv": [8, 12, 8.5, 15], "texture": "#3"},
				"up": {"uv": [11, 4.5, 10.5, 4], "texture": "#3"},
				"down": {"uv": [11, 4.5, 10.5, 5], "texture": "#3"}
			}
		},
		{
			"from": [10, 0, 9],
			"to": [11, 6, 10],
			"faces": {
				"north": {"uv": [11, 4, 11.5, 7], "texture": "#3"},
				"east": {"uv": [11, 7, 11.5, 10], "texture": "#3"},
				"south": {"uv": [11, 10, 11.5, 13], "texture": "#3"},
				"west": {"uv": [11.5, 4, 12, 7], "texture": "#3"},
				"up": {"uv": [10.5, 4.5, 10, 4], "texture": "#3"},
				"down": {"uv": [10.5, 4.5, 10, 5], "texture": "#3"}
			}
		},
		{
			"from": [6, 0, 9],
			"to": [7, 6, 10],
			"faces": {
				"north": {"uv": [8.5, 12, 9, 15], "texture": "#3"},
				"east": {"uv": [9, 12, 9.5, 15], "texture": "#3"},
				"south": {"uv": [12, 9, 12.5, 12], "texture": "#3"},
				"west": {"uv": [9.5, 12, 10, 15], "texture": "#3"},
				"up": {"uv": [11, 5.5, 10.5, 5], "texture": "#3"},
				"down": {"uv": [11, 5.5, 10.5, 6], "texture": "#3"}
			}
		},
		{
			"from": [8, 6.5, 7],
			"to": [9, 7.5, 8],
			"faces": {
				"north": {"uv": [10, 12, 10.5, 12.5], "texture": "#3"},
				"east": {"uv": [10.5, 12, 11, 12.5], "texture": "#3"},
				"south": {"uv": [12.5, 1.5, 13, 2], "texture": "#3"},
				"west": {"uv": [12.5, 2, 13, 2.5], "texture": "#3"},
				"up": {"uv": [13, 3, 12.5, 2.5], "texture": "#3"},
				"down": {"uv": [13, 3, 12.5, 3.5], "texture": "#3"}
			}
		},
		{
			"from": [5.5, 6, 4.5],
			"to": [11.5, 7, 10.5],
			"faces": {
				"north": {"uv": [12, 12, 15, 12.5], "texture": "#3"},
				"east": {"uv": [12.5, 0, 15.5, 0.5], "texture": "#3"},
				"south": {"uv": [12.5, 0.5, 15.5, 1], "texture": "#3"},
				"west": {"uv": [12.5, 1, 15.5, 1.5], "texture": "#3"},
				"up": {"uv": [10, 3, 7, 0], "texture": "#3"},
				"down": {"uv": [10, 3, 7, 6], "texture": "#3"}
			}
		},
		{
			"from": [1, -0.1, 1],
			"to": [15, -0.1, 15],
			"faces": {
				"north": {"uv": [0, 0, 7, 0], "texture": "#3"},
				"east": {"uv": [0, 0, 7, 0], "texture": "#3"},
				"south": {"uv": [0, 0, 7, 0], "texture": "#3"},
				"west": {"uv": [0, 0, 7, 0], "texture": "#3"},
				"up": {"uv": [7, 7, 0, 0], "texture": "#3"},
				"down": {"uv": [7, 7, 0, 14], "texture": "#3"}
			}
		}
	],
	"groups": [
		{
			"name": "all",
			"origin": [8, 8, 8],
			"color": 0,
			"children": [
				{
					"name": "lantern",
					"origin": [8, 8, 8],
					"color": 0,
					"children": [0, 1, 2, 3, 4]
				},
				{
					"name": "body",
					"origin": [8, 8, 8],
					"color": 0,
					"children": [5, 6]
				},
				{
					"name": "pad",
					"origin": [8, 8, 8],
					"color": 0,
					"children": [7]
				}
			]
		}
	]
}